l16_simpleROM/verilog/rom.v
`timescale 1ns/1ps

module rom (
  input [3:0] addr,
  output reg [5:0] data 
);

always @(*)
begin
	case(addr)
        	0: data = 6'd0;
		1: data = 6'd1;
		2: data = 6'd1;
		3: data = 6'd2;
		4: data = 6'd3;
		5: data = 6'd5;
		6: data = 6'd8;
		7: data = 6'd13;
		8: data = 6'd21;
		9: data = 6'd34;
	endcase
end
endmodule

l16_simpleROM/verilog/rom_tb.v
`timescale 1ns / 1ps

module rom_tb;

   reg  [3:0] addr;
   wire [5:0] data;

   rom  simplerom(
		    .addr(addr),
		    .data(data)
		    );

   initial begin

      $dumpfile("top.vcd");
      $dumpvars();

	addr = 4'd0;
	#10;	
	
	addr = 4'd1;
	#10;
	
	addr = 4'd2;
	#10;
	
	addr = 4'd3;
	#10;

	addr = 4'd4;
	#10;

	addr = 4'd5;
	#10;

	addr = 4'd6;
	#10;
	
	addr = 4'd7;
	#10;
	
	addr = 4'd8;     
	#10;
	
	addr = 4'd9;     
	#10;

      $finish;
      
    end 
// initial begin
   
endmodule

l16_simpleROM/verilog/top.vcd
$date
	Thu Nov  7 06:42:46 2019
$end
$version
	Icarus Verilog
$end
$timescale
	1ps
$end
$scope module rom_tb $end
$var wire 6 ! data [5:0] $end
$var reg 4 " addr [3:0] $end
$scope module simplerom $end
$var wire 4 # addr [3:0] $end
$var reg 6 $ data [5:0] $end
$upscope $end
$upscope $end
$enddefinitions $end
#0
$dumpvars
b0 $
b0 #
b0 "
b0 !
$end
#10000
b1 !
b1 $
b1 "
b1 #
#20000
b10 "
b10 #
#30000
b10 !
b10 $
b11 "
b11 #
#40000
b11 !
b11 $
b100 "
b100 #
#50000
b101 !
b101 $
b101 "
b101 #
#60000
b1000 !
b1000 $
b110 "
b110 #
#70000
b1101 !
b1101 $
b111 "
b111 #
#80000
b10101 !
b10101 $
b1000 "
b1000 #
#90000
b100010 !
b100010 $
b1001 "
b1001 #
