Test1/3/a/filters.v
`timescale 1ns/1ps

module filters (
                  input x_is_valid,
                  input [3:0] x,
		          input rst,
		          input clk,
                  output reg [5:0] y 
                  );
 
   reg [3:0]	x1, x2;

   always @(posedge clk) begin 
	if (rst)
	begin
		y<=6'd0;
		x1<=4'd0;
	end
	
	else
	
	if (x_is_valid)
	begin
		x1<=x>>1;
		x2<=x>>3;
		y<=x2;
	end	
   end
	
endmodule

Test1/3/a/filters_tb.v
`timescale 1ns/1ps

module filters_tb ();
 

   reg clk, rst;
   reg x_is_valid;
   reg [3:0] x;
   wire y;

   filters filts(
		.x_is_valid(x_is_valid),
		.clk(clk),
		.rst(rst),
		.x(x),
		.y(y)
		);


   initial begin

      $dumpfile("dump.vcd");
      $dumpvars;

      rst = 1;
      clk = 1;

      x = 4'b0101;

      @(posedge clk) rst=0;


      @(posedge clk) x = 4'b0111;
      @(posedge clk) x = 4'b0100;
      @(posedge clk) x = 4'b1000;
      @(posedge clk) x = 4'b1111;
      @(posedge clk) x_is_valid = 1;


      @(posedge clk) $finish;
   end

   always #10 clk = ~clk;

endmodule

Test1/3/a/dump.vcd
$date
	Thu Nov 21 09:42:48 2019
$end
$version
	Icarus Verilog
$end
$timescale
	1ps
$end
$scope module filters_tb $end
$var wire 1 ! y $end
$var reg 1 " clk $end
$var reg 1 # rst $end
$var reg 4 $ x [3:0] $end
$var reg 1 % x_is_valid $end
$scope module filts $end
$var wire 1 " clk $end
$var wire 1 # rst $end
$var wire 4 & x [3:0] $end
$var wire 1 % x_is_valid $end
$var reg 4 ' x1 [3:0] $end
$var reg 4 ( x2 [3:0] $end
$var reg 6 ) y [5:0] $end
$upscope $end
$upscope $end
$enddefinitions $end
#0
$dumpvars
b0 )
bx (
b0 '
b101 &
x%
b101 $
1#
1"
0!
$end
#10000
0"
#20000
0#
1"
#30000
0"
#40000
b111 $
b111 &
1"
#50000
0"
#60000
b100 $
b100 &
1"
#70000
0"
#80000
b1000 $
b1000 &
1"
#90000
0"
#100000
b1111 $
b1111 &
1"
#110000
0"
#120000
x!
b0xxxx )
b1 (
b111 '
1%
1"
#130000
0"
#140000
1!
b1 )
1"
